masq/__init__.py
masq/const.py
masq/contour.py
masq/generator.py
masq/marching_squares.py
masq/noise.py
masq/point.py
masq-0.0.2.dist-info/LICENSE
masq-0.0.2.dist-info/METADATA
masq-0.0.2.dist-info/WHEEL
masq-0.0.2.dist-info/top_level.txt
masq-0.0.2.dist-info/RECORD
