Metadata-Version: 2.1
Name: masq
Version: 0.0.2
Summary: Marching Squares implementation by Python
Home-page: https://github.com/MorvanZhou/marchingSquares
Author: MorvanZhou
Author-email: morvanzhou@hotmail.com
Project-URL: Bug Tracker, https://github.com/MorvanZhou/marchingSquares/issues
Classifier: Programming Language :: Python :: 3
Classifier: License :: OSI Approved :: MIT License
Classifier: Operating System :: OS Independent
Requires-Python: >=3.7
License-File: LICENSE
Requires-Dist: opensimplex (>=0.4.3)
Requires-Dist: numpy (>=1.22)
Provides-Extra: build
Requires-Dist: tox (==3.24.3) ; extra == 'build'
Requires-Dist: build ; extra == 'build'
Requires-Dist: twine ; extra == 'build'
Requires-Dist: pylint ; extra == 'build'
